[
  {
    "nome": "Astaroth",
    "jogador": "André",
    "n_reg_pokedex": 64,
    "alinhamento": "Leal e Mau",
    "classe": ["Treinador", "Lutador"],
    "nivel": 7,
    "titulo_ou_afiliacao": null,
    "status": {
      "saude": 11,
      "ataque": 17,
      "defesa": 10,
      "ataque_especial": 16,
      "defesa_especial": 9,
      "velocidade": 10
    },
    "pontos_de_vida": 72,
    "dano_de_armas": null,
    "evasao": {
      "fisica": 2,
      "especial": 1,
      "veloz": 2
    },
    "deslocamentos": {
      "terrestre": 5,
      "escavacao": 0,
      "natacao": 4,
      "subaquatico": 3,
      "voo": 0
    },
    "pericias": ["História", "Investigação", "Manha"],
    "talentos": [
      "Armas",
      "Pokedex",
      "Ataques Aprimorados",
      "Treinamento Aprimorado",
      "Dê Tudo de Si!",
      "Rotina de Exercícios",
      "Exercício Brutal",
      "Crítica Construtiva",
      "Ataques Aprimorados +",
      "Já Ouvi Falar!",
      "Galera Vê Só",
      "Rotina de Exercícios"
    ],
    "pokemons": [
      {
        "nome": "Absol",
        "treinador": "Astaroth",
        "nature": "Adamant",
        "tipo": ["Dark"],
        "nivel": 51,
        "pontos_de_vida": 264,
        "status": {
          "saude": 15,
          "ataque": 36,
          "defesa": 14,
          "atq_esp": 4,
          "def_esp": 16,
          "velocidade": 17
        },
        "evasao": {
          "fisica": 5,
          "especial": 7,
          "veloz": 7
        },
        "bonus_elemental": 10,
        "ataques": [
          "Mordida",
          "Lâmina de Vento",
          "Retalhar",
          "Cabeçada Zen",
          "Dança das Espadas",
          "Corte Psíquico",
          "Multiplicar",
          "Emboscada"
        ],
        "habilidades": ["Sorte", "Pressão"],
        "caracteristicas": ["Aura", "Faro", "Silêncio"]
      },
      {
        "nome": "Scizor",
        "treinador": "Astaroth",
        "nature": "Adamant",
        "tipo": ["Inseto", "Metal"],
        "nivel": 51,
        "pontos_de_vida": 256,
        "status": {
          "saude": 13,
          "ataque": 40,
          "defesa": 17,
          "atq_esp": 4,
          "def_esp": 16,
          "velocidade": 12
        },
        "evasao": {
          "fisica": 7,
          "especial": 7,
          "veloz": 7
        },
        "bonus_elemental": 10,
        "ataques": [
          "Metalizar Garra",
          "Lâmina de Vento",
          "Emboscada",
          "Corte em X",
          "Ataque de Asa",
          "Ataque Rápido",
          "Perseguição",
          "Agilidade"
        ],
        "habilidades": ["Técnica", "Metal Leve"],
        "caracteristicas": null
      },
      {
        "nome": "Marowak-Alola",
        "treinador": "Astaroth",
        "nature": "Adamant",
        "tipo": ["Fogo", "Fantasma"],
        "nivel": 51,
        "pontos_de_vida": 260,
        "status": {
          "saude": 14,
          "ataque": 30,
          "defesa": 20,
          "atq_esp": 6,
          "def_esp": 15,
          "velocidade": 9
        },
        "evasao": {
          "fisica": 8,
          "especial": 8,
          "veloz": 5
        },
        "bonus_elemental": 10,
        "ataques": [
          "Cólera",
          "Açoite",
          "Osso Sombrio",
          "Anel de Fogo",
          "Feitiço",
          "Fogo-Fátuo",
          "Onda de Calor",
          "Trocar de Lugar"
        ],
        "habilidades": ["Cabeça Dura", "Pararraios"],
        "caracteristicas": ["Alcance", "Hierarquia"]
      }
    ]
  },
  {
    "nome": "Jin",
    "jogador": "Marcos",
    "n_reg_pokedex": 64,
    "alinhamento": "Leal e Mau",
    "classe": ["Treinador", "Lutador"],
    "nivel": 7,
    "titulo_ou_afiliacao": null,
    "status": {
      "saude": 11,
      "ataque": 17,
      "defesa": 10,
      "ataque_especial": 16,
      "defesa_especial": 9,
      "velocidade": 10
    },
    "pontos_de_vida": 72,
    "dano_de_armas": null,
    "evasao": {
      "fisica": 2,
      "especial": 1,
      "veloz": 2
    },
    "deslocamentos": {
      "terrestre": 5,
      "escavacao": 0,
      "natacao": 4,
      "subaquatico": 3,
      "voo": 0
    },
    "pericias": ["História", "Investigação", "Manha"],
    "talentos": [
      "Armas",
      "Pokedex",
      "Ataques Aprimorados",
      "Treinamento Aprimorado",
      "Dê Tudo de Si!",
      "Rotina de Exercícios",
      "Exercício Brutal",
      "Crítica Construtiva",
      "Ataques Aprimorados +",
      "Já Ouvi Falar!",
      "Galera Vê Só",
      "Rotina de Exercícios"
    ],
    "pokemons": [
      {
        "nome": "Weavile",
        "treinador": "Marcos",
        "nature": "Adamant",
        "tipo": ["Dark"],
        "nivel": 51,
        "pontos_de_vida": 264,
        "status": {
          "saude": 15,
          "ataque": 36,
          "defesa": 14,
          "atq_esp": 4,
          "def_esp": 16,
          "velocidade": 17
        },
        "evasao": {
          "fisica": 5,
          "especial": 7,
          "veloz": 7
        },
        "bonus_elemental": 10,
        "ataques": [
          "Mordida",
          "Lâmina de Vento",
          "Retalhar",
          "Cabeçada Zen",
          "Dança das Espadas",
          "Corte Psíquico",
          "Multiplicar",
          "Emboscada"
        ],
        "habilidades": ["Sorte", "Pressão"],
        "caracteristicas": ["Aura", "Faro", "Silêncio"]
      },
      {
        "nome": "Umbreon",
        "treinador": "Marcos",
        "nature": "Adamant",
        "tipo": ["Inseto", "Metal"],
        "nivel": 51,
        "pontos_de_vida": 256,
        "status": {
          "saude": 13,
          "ataque": 40,
          "defesa": 17,
          "atq_esp": 4,
          "def_esp": 16,
          "velocidade": 12
        },
        "evasao": {
          "fisica": 7,
          "especial": 7,
          "veloz": 7
        },
        "bonus_elemental": 10,
        "ataques": [
          "Metalizar Garra",
          "Lâmina de Vento",
          "Emboscada",
          "Corte em X",
          "Ataque de Asa",
          "Ataque Rápido",
          "Perseguição",
          "Agilidade"
        ],
        "habilidades": ["Técnica", "Metal Leve"],
        "caracteristicas": ["Aura", "Faro", "Silêncio"]
      }
    ]
  }
]
